setup.cfg
setup.py
otpad/__init__.py
otpad/otpad.py
otpad/test_onetimepad.py
otpad.egg-info/PKG-INFO
otpad.egg-info/SOURCES.txt
otpad.egg-info/dependency_links.txt
otpad.egg-info/requires.txt
otpad.egg-info/top_level.txt